agents/__init__.py
agents/bandit_agents.py
agents/base_agents.py
agents/utils.py
games/__init__.py
games/base_games.py
games/utils.py
games/variant_games.py
worlds/__init__.py
worlds/bandit_worlds.py
worlds/base_worlds.py
worlds/epidemic_worlds.py
worlds/utils.py
banditzoo-0.0.6.dist-info/LICENSE
banditzoo-0.0.6.dist-info/METADATA
banditzoo-0.0.6.dist-info/WHEEL
banditzoo-0.0.6.dist-info/top_level.txt
banditzoo-0.0.6.dist-info/RECORD
