Metadata-Version: 2.1
Name: banditzoo
Version: 0.0.6
Summary: Python library of bandits and RL agents in different real-world environments
Home-page: https://github.com/doerlbh/BanditZoo
Author: Baihan Lin
Author-email: doerlbh@gmail.com
License: GPLv3
Project-URL: Bug Tracker, https://github.com/doerlbh/BanditZoo/issues
Platform: UNKNOWN
Classifier: Programming Language :: Python :: 3
Classifier: License :: OSI Approved :: GNU General Public License v3 (GPLv3)
Classifier: Operating System :: OS Independent
Requires-Python: >=3.6
Requires-Dist: numpy (>=1.16.5)
Requires-Dist: pandas
